tilupy/__init__.py
tilupy/analytic_sol.py
tilupy/benchmark.py
tilupy/calibration.py
tilupy/cmd.py
tilupy/compare.py
tilupy/download_data.py
tilupy/initdata.py
tilupy/initsimus.py
tilupy/make_mass.py
tilupy/make_topo.py
tilupy/notations.py
tilupy/plot.py
tilupy/raster.py
tilupy/read.py
tilupy/utils.py
tilupy/models/__init__.py
tilupy/models/lave2D/__init__.py
tilupy/models/lave2D/initsimus.py
tilupy/models/lave2D/read.py
tilupy/models/ravaflow/__init__.py
tilupy/models/ravaflow/initsimus.py
tilupy/models/ravaflow/read.py
tilupy/models/saval2D/__init__.py
tilupy/models/saval2D/read.py
tilupy/models/shaltop/__init__.py
tilupy/models/shaltop/initsimus.py
tilupy/models/shaltop/read.py
tilupy-2.0.1.dist-info/licenses/LICENSE
tilupy-2.0.1.dist-info/METADATA
tilupy-2.0.1.dist-info/WHEEL
tilupy-2.0.1.dist-info/entry_points.txt
tilupy-2.0.1.dist-info/top_level.txt
tilupy-2.0.1.dist-info/RECORD
