Metadata-Version: 2.4
Name: tilupy
Version: 2.0.1
Summary: Thin-layer models unified processing tool
Author-email: Marc Peruzzetto <m.peruzzetto@brgm.fr>
License: CeCILL-C FREE SOFTWARE LICENSE AGREEMENT
Project-URL: Homepage, https://github.com/marcperuz/tilupy
Keywords: thin-layer,shallow-water,display,simulation,model,processing,benchmark
Classifier: License :: CeCILL-C Free Software License Agreement (CECILL-C)
Classifier: Programming Language :: Python
Classifier: Programming Language :: Python :: 3
Requires-Python: >=3.10
License-File: LICENSE
Requires-Dist: seaborn
Requires-Dist: requests
Requires-Dist: scipy
Requires-Dist: pytopomap
Requires-Dist: shapely
Requires-Dist: rasterio
Provides-Extra: test
Requires-Dist: pytest; extra == "test"
Provides-Extra: dev
Requires-Dist: pipreqs; extra == "dev"
Provides-Extra: gis
Requires-Dist: rasterio; extra == "gis"
Requires-Dist: shapely; extra == "gis"
Dynamic: license-file
